pyensmallen/newton_type.hpp
pyensmallen/gmm.py
pyensmallen/_pyensmallen.cpython-310-darwin.so
pyensmallen/__init__.py
pyensmallen/first_order.hpp
pyensmallen/losses.py
pyensmallen/constrained.hpp
pyensmallen/utils.hpp
pyensmallen/.dylibs/libarpack.2.1.0.dylib
pyensmallen/.dylibs/libomp.dylib
pyensmallen/.dylibs/libgfortran.5.dylib
pyensmallen/.dylibs/libquadmath.0.dylib
pyensmallen/.dylibs/libgcc_s.1.1.dylib
pyensmallen/.dylibs/libarmadillo.14.6.0.dylib
pyensmallen/.dylibs/libopenblas.0.dylib
pyensmallen-0.3.2.dist-info/RECORD
pyensmallen-0.3.2.dist-info/WHEEL
pyensmallen-0.3.2.dist-info/LICENSE.txt
pyensmallen-0.3.2.dist-info/METADATA
