Metadata-Version: 2.1
Name: pyensmallen
Version: 0.3.2
Summary: Python bindings for the Ensmallen library.
Author-Email: Apoorva Lal <lal.apoorva@gmail.com>, Matthew Wardrop <mpwardrop@gmail.com>
License: MIT License
Requires-Python: >=3.10
Provides-Extra: gmm
Requires-Dist: jax; extra == "gmm"
Requires-Dist: jaxlib; extra == "gmm"
